{
    "phrase_lookup": {
        "sold out": "unavailable",
        "out of stock": "unavailable",
        "pack back": "takeaway",
        "okay je": "just okay",
        "ok je": "just okay",
        "klu tahu": "if i knew",
        "kalau tahu": "if i knew"
    },
    "word_lookup": {
        "x": "not",
        "tk": "not",
        "tak": "not",
        "bagi": "give",
        "bgi": "give",
        "pon": "also",
        "pun": "also",
        "dah": "already",
        "dh": "already",
        "nk": "want",
        "nak": "want",
        "je": "only",
        "jee": "only",
        "aje": "only",
        "skg": "now",
        "skali": "once",
        "org": "people",
        "kau": "you",
        "sya": "I",
        "sy": "me",
        "dpt": "get",
        "ni": "this",
        "klu": "if",
        "thu": "know",
        "tahu": "know",
        "mkn": "eat",
        "nau": "very",
        "mmg": "indeed",
        "tmpt": "place",
        "sdp": "tasty",
        "gi": "go",
        "prgi": "go",
        "trk": "bad",
        "sgt": "very",
        "prsn": "noticed",
        "stf": "staff",
        "msk": "enter",
        "kt": "at",
        "kat": "at",
        "kawkaw": "amazing",
        "kaw": "amazing",
        "pekat": "strong",
        "power": "excellent",
        "best": "great",
        "gempak": "awesome",
        "ngam": "perfect",
        "cun": "good",
        "tapau": "takeaway",
        "bungkus": "takeaway",
        "lambat": "slow",
        "ptut": "supposed",
        "out": "bad",
        "masuk": "enter",
        "bapak": "extremely",
        "lembap": "slow",
        "semuanya": "everyone",
        "agak": "quite",
        "agk": "quite",
        "lantai": "floor",
        "padu": "awesome",
        "mau": "want",
        "langsung": "at all",
        "lgsng": "at all",
        "mslh": "problem",
        "mantap": "excellent",
        "kedia": "shop"
    },
    "noise_particles": [
        "lah",
        "la",
        "weh",
        "sia",
        "doh",
        "leh"
    ]
}